django_fabfile
