Metadata-Version: 1.1
Name: django-fabfile
Version: 2013.08.29.2
Summary: Fabric tasks for Django and Amazon Web Services
Home-page: http://packages.python.org/django-fabfile
Author: Max Chervonec
Author-email: electedm@odesk.com
License: GNU GPLv3
Download-URL: http://pypi.python.org/pypi/django-fabfile/
Platform: UNKNOWN
Classifier: Development Status :: 5 - Production/Stable
Classifier: Environment :: Web Environment
Classifier: Framework :: Django
Classifier: Intended Audience :: Developers
Classifier: Intended Audience :: System Administrators
Classifier: License :: OSI Approved :: GNU General Public License v3 (GPLv3)
Classifier: Operating System :: OS Independent
Classifier: Programming Language :: Python
Classifier: Topic :: Software Development :: Libraries :: Python Modules
Classifier: Topic :: System :: Clustering
Classifier: Topic :: System :: Software Distribution
Classifier: Topic :: System :: Systems Administration
